docs/__init__.py
docs/conf.py
docs/gen_docs.py
docs/index.rst
fetrix-0.0.1a0.dist-info/DESCRIPTION.rst
fetrix-0.0.1a0.dist-info/METADATA
fetrix-0.0.1a0.dist-info/RECORD
fetrix-0.0.1a0.dist-info/WHEEL
fetrix-0.0.1a0.dist-info/entry_points.txt
fetrix-0.0.1a0.dist-info/metadata.json
fetrix-0.0.1a0.dist-info/top_level.txt
ibvpy/__init__.py
ibvpy/api.py
ibvpy/bcond/__init__.py
ibvpy/bcond/bc_dof.py
ibvpy/bcond/bc_dofgroup.py
ibvpy/bcond/bc_slice.py
ibvpy/bcond/demos.py
ibvpy/bcond/test_nose.py
ibvpy/cntl/__init__.py
ibvpy/cntl/displ_avg/3pt_bending2d_mdm.py
ibvpy/cntl/displ_avg/3pt_bending2d_sdamage.py
ibvpy/cntl/displ_avg/3pt_bending_adapted.py
ibvpy/cntl/displ_avg/__init__.py
ibvpy/cntl/displ_avg/bar1d_damage.py
ibvpy/cntl/displ_avg/bar1d_elastic.py
ibvpy/cntl/displ_avg/rt_nonlocal_averaging.py
ibvpy/core/__init__.py
ibvpy/core/api.py
ibvpy/core/astrategy.py
ibvpy/core/bcond_mngr.py
ibvpy/core/i_bcond.py
ibvpy/core/i_sdomain.py
ibvpy/core/i_tstepper_eval.py
ibvpy/core/ibv_model.py
ibvpy/core/ibv_resource.py
ibvpy/core/ibvp_solve.py
ibvpy/core/rtrace.py
ibvpy/core/rtrace_eval.py
ibvpy/core/rtrace_mngr.py
ibvpy/core/scontext.py
ibvpy/core/sdomain.py
ibvpy/core/tloop.py
ibvpy/core/tstepper.py
ibvpy/core/tstepper_eval.py
ibvpy/core/ui/__init__.py
ibvpy/core/ui/tstepper_view.py
ibvpy/dots/__init__.py
ibvpy/dots/dots_eval.py
ibvpy/dots/dots_eval_avg.py
ibvpy/dots/dots_list_eval.py
ibvpy/dots/dots_unstructured_eval.py
ibvpy/dots/subdots_eval.py
ibvpy/dots/xdots_eval.py
ibvpy/dots/examples/__init__.py
ibvpy/dots/examples/dots_list_examples.py
ibvpy/fets/__init__.py
ibvpy/fets/fets_eval.py
ibvpy/fets/fets_eval_prototyped.py
ibvpy/fets/i_fets_eval.py
ibvpy/fets/xfets_eval.py
ibvpy/fets/fets1D/__init__.py
ibvpy/fets/fets1D/fets1D2l.py
ibvpy/fets/fets1D/fets1D2l3u.py
ibvpy/fets/fets1D5/__init__.py
ibvpy/fets/fets1D5/fets1D52l4uLRH.py
ibvpy/fets/fets1D5/fets1D52l6uLRH.py
ibvpy/fets/fets1D5/fets1D52l8uLRH.py
ibvpy/fets/fets2D/__init__.py
ibvpy/fets/fets2D/fets2D4q.py
ibvpy/fets/fets2D/fets2D4q12u.py
ibvpy/fets/fets2D/fets2D4q16u.py
ibvpy/fets/fets2D/fets2D4q4t.py
ibvpy/fets/fets2D/fets2D4q8u.py
ibvpy/fets/fets2D/fets2D4q9u.py
ibvpy/fets/fets2D/fets2D9q.py
