Metadata-Version: 2.0
Name: fetrix
Version: 0.0.1a0
Summary: Initial boundary value problem yolver using generic finite element scripting core.
Home-page: http://packages.python.org/bmcs
Author: Rostislav Chudoba
Author-email: rostislav.chudoba@rwth-aachen.de
License: BSD
Keywords: looples finite elements
Platform: UNKNOWN
Classifier: Development Status :: 3 - Alpha
Classifier: Topic :: Utilities
Classifier: License :: OSI Approved :: BSD License
Requires-Dist: matplotlib (>=1.5.3)
Requires-Dist: numpy (>=1.10.0)
Requires-Dist: pyface (>=4.0.0)
Requires-Dist: scipy (>=0.18.1)
Requires-Dist: sympy (>=1.0)
Requires-Dist: traits (>=4.0.0)
Requires-Dist: traitsui (>=4.0.0)
